pydantic_validation_decorator/__init__.py
pydantic_validation_decorator/alpha.py
pydantic_validation_decorator/exceptions.py
pydantic_validation_decorator/network.py
pydantic_validation_decorator/not_blank.py
pydantic_validation_decorator/pattern.py
pydantic_validation_decorator/size.py
pydantic_validation_decorator/utils.py
pydantic_validation_decorator/validation.py
pydantic_validation_decorator/xss.py
pydantic_validation_decorator-0.1.5.dist-info/licenses/LICENSE
tests/__init__.py
tests/test_alpha_decorator.py
tests/test_network_decorator.py
tests/test_not_blank_decorator.py
tests/test_pattern_decorator.py
tests/test_size_decorator.py
tests/test_xss_decorator.py
pydantic_validation_decorator-0.1.5.dist-info/METADATA
pydantic_validation_decorator-0.1.5.dist-info/WHEEL
pydantic_validation_decorator-0.1.5.dist-info/top_level.txt
pydantic_validation_decorator-0.1.5.dist-info/RECORD
