Metadata-Version: 2.4
Name: pydantic-validation-decorator
Version: 0.1.5
Summary: Some practical pydantic validation decorators that support manual invocation.
Home-page: https://github.com/insistence/pydantic-validation-decorator
Author: insistence <3055204202@qq.com>
Author-email: 3055204202@qq.com
License: MIT
Classifier: Framework :: Pydantic
Classifier: Programming Language :: Python
Classifier: Topic :: Software Development :: Libraries :: Python Modules
Requires-Python: >=3.8
License-File: LICENSE
Requires-Dist: pydantic[email]>=2.7.1
Dynamic: author
Dynamic: author-email
Dynamic: classifier
Dynamic: description
Dynamic: description-content-type
Dynamic: home-page
Dynamic: license
Dynamic: license-file
Dynamic: requires-dist
Dynamic: requires-python
Dynamic: summary
